st_files_connection/__init__.py
st_files_connection/connection.py
st_files_connection-0.1.0.dist-info/LICENSE
st_files_connection-0.1.0.dist-info/METADATA
st_files_connection-0.1.0.dist-info/WHEEL
st_files_connection-0.1.0.dist-info/top_level.txt
st_files_connection-0.1.0.dist-info/RECORD
