Metadata-Version: 2.1
Name: st-files-connection
Version: 0.1.0
Summary: Streamlit Connection for cloud and remote file storage.
Home-page: https://github.com/streamlit/files-connection
Author: Snowflake Inc
Author-email: hello@streamlit.io
License: Apache License 2.0
Project-URL: Source Code, https://github.com/streamlit/files-connection
Classifier: Development Status :: 3 - Alpha
Classifier: Environment :: Console
Classifier: Environment :: Web Environment
Classifier: Intended Audience :: Developers
Classifier: Intended Audience :: Science/Research
Classifier: License :: OSI Approved :: Apache Software License
Classifier: Programming Language :: Python :: 3.8
Classifier: Programming Language :: Python :: 3.9
Classifier: Programming Language :: Python :: 3.10
Requires-Python: >=3.8
License-File: LICENSE
